my_math_lib/__init__.py
my_math_lib/operations.py
my_math_lib_ram-0.1.0.dist-info/LICENSE.txt
my_math_lib_ram-0.1.0.dist-info/METADATA
my_math_lib_ram-0.1.0.dist-info/WHEEL
my_math_lib_ram-0.1.0.dist-info/top_level.txt
my_math_lib_ram-0.1.0.dist-info/RECORD
